conformal_region_designer/__init__.py
conformal_region_designer/case_studies/__init__.py
conformal_region_designer/case_studies/car_experiments/__init__.py
conformal_region_designer/case_studies/car_experiments/car_env.py
conformal_region_designer/case_studies/car_experiments/data_generation.py
conformal_region_designer/case_studies/car_experiments/predictor.py
conformal_region_designer/case_studies/f16/data/all_data.pkl
conformal_region_designer/case_studies/f16/data/calib_data.pkl
conformal_region_designer/case_studies/f16/data/stackedOutput/3400DataPoints/pred_future_window_25/skip_step_3/x_test.pkl
conformal_region_designer/case_studies/f16/data/stackedOutput/3400DataPoints/pred_future_window_25/skip_step_3/x_train.pkl
conformal_region_designer/case_studies/f16/data/stackedOutput/3400DataPoints/pred_future_window_25/skip_step_3/y_test.pkl
conformal_region_designer/case_studies/f16/data/stackedOutput/3400DataPoints/pred_future_window_25/skip_step_3/y_train.pkl
conformal_region_designer/case_studies/f16/data/testResiduals/residuals.pkl
conformal_region_designer/case_studies/f16/images/stackedOutput/3400DataPoints/pred_future_window_25/skip_step_3/alt_theta/scatterPlotTestErrs.png
conformal_region_designer/case_studies/f16/models/firstTryLSTMScaler_alt_theta.pkl
conformal_region_designer/case_studies/f16/models/stackedOutput/3400DataPoints/pred_future_window_25/skip_step_3/firstTryLSTM_alt_theta_hAndc.pt
conformal_region_designer/case_studies/f16/myLSTM.py
conformal_region_designer/case_studies/f16/runProcedureOnResiduals.py
conformal_region_designer/case_studies/f16/train_lstm_stacked_output.py
conformal_region_designer/clustering.py
conformal_region_designer/conformity_optimizer.py
conformal_region_designer/core.py
conformal_region_designer/density_estimation.py
conformal_region_designer/shapes/__init__.py
conformal_region_designer/shapes/convexhull.py
conformal_region_designer/shapes/ellipse.py
conformal_region_designer/shapes/hyperrectangle.py
conformal_region_designer-0.1.2.dist-info/LICENSE
conformal_region_designer-0.1.2.dist-info/METADATA
conformal_region_designer-0.1.2.dist-info/WHEEL
conformal_region_designer-0.1.2.dist-info/RECORD
